README.rst
setup.py
envious/__init__.py
envious/load.py
envious.egg-info/PKG-INFO
envious.egg-info/SOURCES.txt
envious.egg-info/dependency_links.txt
envious.egg-info/top_level.txt