Metadata-Version: 1.0
Name: envious
Version: 0.1
Summary: Easy injection of environment variables from .env files.
Home-page: UNKNOWN
Author: Matteo Danieli
Author-email: md@bendingspoons.dk
License: UNKNOWN
Platform: UNKNOWN
